watched_schema/__init__.py
watched_schema/schema.yaml
watched_schema-0.6.2.dist-info/METADATA
watched_schema-0.6.2.dist-info/WHEEL
watched_schema-0.6.2.dist-info/top_level.txt
watched_schema-0.6.2.dist-info/RECORD
