Metadata-Version: 2.1
Name: watched-schema
Version: 0.6.2
Summary: WATCHED.com JSON Schema
Home-page: https://github.com/watchedcom/schema
Author: WATCHED
Author-email: dev@watched.com
License: UNKNOWN
Platform: UNKNOWN
Requires-Python: >=3.4
Requires-Dist: pyyaml
Requires-Dist: jsonschema
